insardev/Stack.py
insardev/Stack_base.py
insardev/Stack_detrend.py
insardev/Stack_export.py
insardev/Stack_incidence.py
insardev/Stack_lstsq.py
insardev/Stack_multilooking.py
insardev/Stack_phasediff.py
insardev/Stack_plot.py
insardev/Stack_ps.py
insardev/Stack_sbas.py
insardev/Stack_stl.py
insardev/Stack_unwrap.py
insardev/Stack_unwrap_snaphu.py
insardev/UI.py
insardev/__init__.py
insardev/dataset.py
insardev/utils.py
insardev-2025.5.6.dev0.dist-info/licenses/LICENSE
insardev-2025.5.6.dev0.dist-info/METADATA
insardev-2025.5.6.dev0.dist-info/WHEEL
insardev-2025.5.6.dev0.dist-info/top_level.txt
insardev-2025.5.6.dev0.dist-info/RECORD
