Metadata-Version: 2.4
Name: insardev
Version: 2025.5.6.dev0
Summary: InSAR.dev (Python InSAR): Satellite Interferometry Framework
Home-page: https://github.com/AlexeyPechnikov/pygmtsar
Author: Alexey Pechnikov
Author-email: alexey@pechnikov.dev
License: InSAR.dev Personal License
Keywords: satellite interferometry,InSAR,remote sensing,geospatial analysis,elevation,Sentinel-1,SBAS,PSI
Classifier: Development Status :: 4 - Beta
Classifier: Intended Audience :: Science/Research
Classifier: Natural Language :: English
Classifier: License :: Other/Proprietary License
Classifier: Operating System :: POSIX
Classifier: Operating System :: POSIX :: Linux
Classifier: Operating System :: MacOS
Classifier: Programming Language :: Python
Classifier: Programming Language :: Python :: 3.10
Classifier: Programming Language :: Python :: 3.11
Classifier: Programming Language :: Python :: 3.12
Classifier: Programming Language :: Python :: 3.13
Requires-Python: >=3.10
License-File: LICENSE
Requires-Dist: insardev_toolkit
Requires-Dist: xarray
Requires-Dist: numpy
Requires-Dist: numba
Requires-Dist: pandas
Requires-Dist: geopandas
Requires-Dist: distributed
Requires-Dist: dask[complete]
Requires-Dist: zarr
Requires-Dist: scipy
Requires-Dist: xgboost
Requires-Dist: cffi
Requires-Dist: scikit-learn
Requires-Dist: statsmodels>=0.14.0
Requires-Dist: matplotlib
Requires-Dist: adjustText
Requires-Dist: seaborn
Requires-Dist: bottleneck
Requires-Dist: fsspec
Requires-Dist: aiohttp
Dynamic: author
Dynamic: author-email
Dynamic: classifier
Dynamic: description
Dynamic: description-content-type
Dynamic: home-page
Dynamic: keywords
Dynamic: license
Dynamic: license-file
Dynamic: requires-dist
Dynamic: requires-python
Dynamic: summary
